excel_template/Writer.py
excel_template/WriterTemplate.py
excel_template/__init__.py
excel_template-0.1.5.dist-info/LICENSE
excel_template-0.1.5.dist-info/METADATA
excel_template-0.1.5.dist-info/WHEEL
excel_template-0.1.5.dist-info/top_level.txt
excel_template-0.1.5.dist-info/RECORD
