Metadata-Version: 2.1
Name: excel-template
Version: 0.1.5
Summary: Create Excel file according to the Excel template which fits a specific format
Home-page: https://github.com/qjjayy/excel_template
Author: Junjie Qiu
Author-email: xiaohaixie@qq.com
License: MIT
Keywords: excel template render
Platform: any
Classifier: Intended Audience :: Developers
Classifier: License :: OSI Approved :: MIT License
Classifier: Programming Language :: Python :: 2.7
Requires-Dist: openpyxl
